collektions-1.1.1.dist-info/METADATA
collektions-1.1.1.dist-info/WHEEL
collektions-1.1.1.dist-info/entry_points.txt
collektions/__init__.py
collektions/_defaults.py
collektions/_iterable.py
collektions/_mapping.py
collektions/_sequence.py
collektions/_types.py
collektions/preconditions.py
collektions/py.typed
collektions/shadow.py
collektions/version.py
collektions-1.1.1.dist-info/RECORD
