Metadata-Version: 2.1
Name: collektions
Version: 1.1.1
Summary: A collection of Python functions on iterables and collections inspired by the Kotlin collections API.
Author-Email: Ryan Smith <ryan.d.smith.106@gmail.com>
Requires-Python: >=3.9
